windIO/__init__.py
windIO/validator.py
windIO/version.py
windIO/yaml.py
windIO/converters/windIO2windIO.py
windIO/examples/__init__.py
windIO/examples/plant/__init__.py
windIO/examples/plant/plant_energy_resource/GriddedResource.nc
windIO/examples/plant/plant_energy_resource/GriddedResource.yaml
windIO/examples/plant/plant_energy_resource/GriddedResource_nc.yaml
windIO/examples/plant/plant_energy_resource/HorizontalProfile.nc
windIO/examples/plant/plant_energy_resource/HourlyVariation_atHubHeight.nc
windIO/examples/plant/plant_energy_resource/HourlyVariation_verticalProfile.nc
windIO/examples/plant/plant_energy_resource/IEA37_case_study_1_2_energy_resource.yaml
windIO/examples/plant/plant_energy_resource/IEA37_case_study_3_energy_resource.yaml
windIO/examples/plant/plant_energy_resource/IEA37_case_study_4_energy_resource.yaml
windIO/examples/plant/plant_energy_resource/InflowMap_xz.nc
windIO/examples/plant/plant_energy_resource/Stochastic_atHubHeight.nc
windIO/examples/plant/plant_energy_resource/Stochastic_vertical_profiles.nc
windIO/examples/plant/plant_energy_resource/UniformResource.nc
windIO/examples/plant/plant_energy_resource/UniformResource.yaml
windIO/examples/plant/plant_energy_resource/UniformResource_nc.yaml
windIO/examples/plant/plant_energy_resource/UniformWeibullResource.nc
windIO/examples/plant/plant_energy_resource/UniformWeibullResource.yaml
windIO/examples/plant/plant_energy_resource/UniformWeibullResource_nc.yaml
windIO/examples/plant/plant_energy_resource/WTResource.nc
windIO/examples/plant/plant_energy_resource/WTResource.yaml
windIO/examples/plant/plant_energy_resource/WTResource_nc.yaml
windIO/examples/plant/plant_energy_resource/first_three_times.nc
windIO/examples/plant/plant_energy_resource/timeseries.yaml
windIO/examples/plant/plant_energy_resource/timeseries_vertical_variation.yaml
windIO/examples/plant/plant_energy_resource/timeseries_with_netcdf.yaml
windIO/examples/plant/plant_energy_resource/verticalVariationTimeseries.nc
windio-2.0.1.dist-info/licenses/LICENSE
windio-2.0.1.dist-info/METADATA
windio-2.0.1.dist-info/WHEEL
windio-2.0.1.dist-info/top_level.txt
windio-2.0.1.dist-info/RECORD
