Metadata-Version: 2.4
Name: windIO
Version: 2.0.1
Summary: Frameworks defining the inputs and outputs for systems engineering MDAO of wind turbine and plants.
Author: IEA Wind Task 37 and 55
License:                                  Apache License
Project-URL: Homepage, https://github.com/IEAWindSystems/windIO
Project-URL: Documentation, https://ieawindsystems.github.io/windio
Keywords: windIO
Classifier: License :: OSI Approved :: Apache Software License
Classifier: Programming Language :: Python
Classifier: Programming Language :: Python :: 3
Classifier: Programming Language :: Python :: 3.9
Classifier: Programming Language :: Python :: 3.10
Classifier: Programming Language :: Python :: 3.11
Classifier: Programming Language :: Python :: 3.12
Classifier: Programming Language :: Python :: 3.13
Classifier: Programming Language :: Python :: Implementation :: CPython
Requires-Python: >=3.9
License-File: LICENSE
Requires-Dist: jsonschema
Requires-Dist: ruamel.yaml
Requires-Dist: xarray
Requires-Dist: netcdf4
Provides-Extra: docs
Requires-Dist: sphinx; extra == "docs"
Requires-Dist: pydata-sphinx-theme; extra == "docs"
Requires-Dist: json-schema-for-humans; extra == "docs"
Requires-Dist: gitpython; extra == "docs"
Requires-Dist: sphinx_multiversion; extra == "docs"
Provides-Extra: test
Requires-Dist: numpy; extra == "test"
Requires-Dist: pytest; extra == "test"
Requires-Dist: pytest-subtests; extra == "test"
Requires-Dist: pint; extra == "test"
Requires-Dist: scipy; extra == "test"
Dynamic: license-file
